mdzip/AE.py
mdzip/__init__.py
mdzip/mdzip_core.py
mdzip/quantize.py
mdzip/save.py
mdzip/skipAE.py
mdzip/utils.py
mdzip-0.1.1.dist-info/METADATA
mdzip-0.1.1.dist-info/WHEEL
mdzip-0.1.1.dist-info/entry_points.txt
mdzip-0.1.1.dist-info/top_level.txt
mdzip-0.1.1.dist-info/RECORD
