Metadata-Version: 2.4
Name: mdzip
Version: 0.1.1
Summary: Compress MD trajectories using deep convolutional autoencoder
Home-page: https://github.com/nami-rangana/MolZip.git
Author: Namindu De Silva
Author-email: nami.rangana@gmail.com
Classifier: Programming Language :: Python :: 3
Classifier: Programming Language :: Python :: 3.10
Classifier: License :: OSI Approved :: MIT License
Classifier: Operating System :: OS Independent
Requires-Python: >=3.6
Requires-Dist: wheel
Requires-Dist: mdtraj
Requires-Dist: mdanalysis
Requires-Dist: torch
Requires-Dist: torchvision
Requires-Dist: torchaudio
Requires-Dist: pytorch-lightning
Requires-Dist: scikit-learn
Requires-Dist: numpy
Requires-Dist: tqdm
Requires-Dist: tensorboardX
Requires-Dist: tensorboard
Dynamic: author
Dynamic: author-email
Dynamic: classifier
Dynamic: description
Dynamic: description-content-type
Dynamic: home-page
Dynamic: requires-dist
Dynamic: requires-python
Dynamic: summary
